rklearn/__init__.py
rklearn/adaline.py
rklearn/globals.py
rklearn/model_selection.py
rklearn/neuralnet.py
rklearn/opendata_loaders.py
rklearn/perceptron.py
rklearn/plotters.py
rklearn/tests/__init__.py
rklearn/tests/test_mnist_plotters.py
rklearn/tests/test_plotters.py
rklearn/tests/test_rklearn_adaline_binary_iris_training.py
rklearn/tests/test_rklearn_adaline_binary_mnist.py
rklearn/tests/test_rklearn_adaline_binary_mnist_CV.py
rklearn/tests/test_rklearn_neuralnetmlp_binray_mnist.py
rklearn/tests/test_rklearn_perceptron.py
rklearn/tests/test_rklearn_perceptron_binary_iris_training.py
rklearn/tests/test_rklearn_perceptron_binary_mnist.py
rklearn/tests/test_rklearn_perceptron_binary_mnist_CV.py
rklearn/tests/test_rklearn_sklearn_perceptron_binary_iris_training.py
rklearn-1.0.4.dist-info/LICENSE
rklearn-1.0.4.dist-info/METADATA
rklearn-1.0.4.dist-info/WHEEL
rklearn-1.0.4.dist-info/top_level.txt
rklearn-1.0.4.dist-info/RECORD
